
{"content":[{"id":"6eac4032","settings":{"jet_parallax_layout_list":[],"ee_display_conditions":[{"_id":"90b1861"}],"structure":"20","margin":{"unit":"px","top":"0150","right":0,"bottom":"0","left":0,"isLinked":false}},"elements":[{"id":"7ad57038","settings":{"_column_size":50,"_inline_size":null,"padding":{"unit":"px","top":"40","right":"40","bottom":"40","left":"40","isLinked":true}},"elements":[{"id":"5c94b2c0","settings":{"title":"Calculadora de costo en cuotas","tooltip_content":"I am a tooltip"},"elements":[],"isInner":false,"widgetType":"heading","elType":"widget"},{"id":"2838ae9a","settings":{"tooltip_content":"I am a tooltip"},"elements":[],"isInner":false,"widgetType":"woocommerce-product-images","elType":"widget"},{"id":"118660fb","settings":{"ee_display_conditions":[{"_id":"a90d5c2"}],"tooltip_content":"I am a tooltip","shortcode":"[CalculadoraIndividual]"},"elements":[],"isInner":false,"widgetType":"shortcode","elType":"widget"}],"isInner":false,"elType":"column"},{"id":"6bf99c84","settings":{"_column_size":50,"_inline_size":null},"elements":[{"id":"4d345c85","settings":{"jet_parallax_layout_list":[],"margin":{"unit":"px","top":"0","right":0,"bottom":"0","left":0,"isLinked":false},"padding":{"unit":"px","top":"0","right":"0","bottom":"0","left":"0","isLinked":true}},"elements":[{"id":"7980af90","settings":{"_column_size":100,"_inline_size":null,"_element_id":"loader"},"elements":[],"isInner":true,"elType":"column"}],"isInner":true,"elType":"section"},{"id":"2704c1d4","settings":{"jet_parallax_layout_list":[],"structure":"20","margin":{"unit":"px","top":"100","right":0,"bottom":"0","left":0,"isLinked":false},"padding":{"unit":"px","top":"0","right":"0","bottom":"0","left":"0","isLinked":true}},"elements":[{"id":"1e7c1aec","settings":{"_column_size":50,"_inline_size":null,"_element_id":"loteDetail"},"elements":[{"id":"5b1d83f2","settings":{"title":"Detalles del lote","header_size":"h4","tooltip_content":"I am a tooltip"},"elements":[],"isInner":false,"widgetType":"heading","elType":"widget"},{"id":"1300d80f","settings":{"title":"Detalles del lote","header_size":"h4","tooltip_content":"I am a tooltip","__dynamic__":{"title":"[elementor-tag id=\"efe196e\" name=\"woocommerce-product-title-tag\" settings=\"%7B%7D\"]"}},"elements":[],"isInner":false,"widgetType":"heading","elType":"widget"},{"id":"17ca8b4d","settings":{"title":"Detalles del lote","header_size":"h4","tooltip_content":"I am a tooltip","__dynamic__":{"title":"[elementor-tag id=\"a4fe035\" name=\"woocommerce-product-price-tag\" settings=\"%7B%22before%22%3A%22Valor%3A%20%22%2C%22after%22%3A%22.-%22%7D\"]"}},"elements":[],"isInner":false,"widgetType":"heading","elType":"widget"},{"id":"16d8c4e4","settings":{"title":"Detalles del lote","header_size":"h4","tooltip_content":"I am a tooltip","__dynamic__":{"title":"[elementor-tag id=\"f11eba5\" name=\"jet-term-field\" settings=\"%7B%22taxonomy%22%3A%22product_cat%22%2C%22term_field%22%3A%22name%22%7D\"]"}},"elements":[],"isInner":false,"widgetType":"heading","elType":"widget"}],"isInner":true,"elType":"column"},{"id":"7ef47ee0","settings":{"_column_size":50,"_inline_size":null,"_element_id":"resultDetail"},"elements":[{"id":"26d60104","settings":{"title":"Resumen del calculo","header_size":"h4","tooltip_content":"I am a tooltip"},"elements":[],"isInner":false,"widgetType":"heading","elType":"widget"}],"isInner":true,"elType":"column"}],"isInner":true,"elType":"section"}],"isInner":false,"elType":"column"}],"isInner":false,"elType":"section"}],"page_settings":{"page_template":"elementor_canvas"},"version":"0.4","title":"plantilla_SingleLote","type":"section